<?xml version="1.0" encoding="UTF-8" standalone="yes"?>
<cards>
  <name>WalkerCollection</name>
  <key>Collections/WalkerCollection</key>
  <comment></comment>
  <type></type>
  <properties>
    <property name="virtual" value="false"/>
  </properties>
  <list>
    <mcp>
      <card>
        <id>230071</id>
        <name>Forest</name>
        <edition>New Phyrexia</edition>
      </card>
      <count>21</count>
      <location>Collections/WalkerCollection</location>
      <ownership>true</ownership>
      <date>Sat Jan 30 10:14:23 EST 2016</date>
    </mcp>
    <mcp>
      <card>
        <id>227505</id>
        <name>Island</name>
        <edition>New Phyrexia</edition>
      </card>
      <count>12</count>
      <location>Collections/WalkerCollection</location>
      <ownership>true</ownership>
      <date>Sat Jan 30 10:18:35 EST 2016</date>
    </mcp>
    <mcp>
      <card>
        <id>230064</id>
        <name>Mountain</name>
        <edition>New Phyrexia</edition>
      </card>
      <count>41</count>
      <location>Collections/WalkerCollection</location>
      <ownership>true</ownership>
      <date>Sat Jan 30 10:18:36 EST 2016</date>
    </mcp>
    <mcp>
      <card>
        <id>227518</id>
        <name>Plains</name>
        <edition>New Phyrexia</edition>
      </card>
      <count>13</count>
      <location>Collections/WalkerCollection</location>
      <ownership>true</ownership>
      <date>Sat Jan 30 10:18:38 EST 2016</date>
    </mcp>
    <mcp>
      <card>
        <id>227521</id>
        <name>Swamp</name>
        <edition>New Phyrexia</edition>
      </card>
      <count>15</count>
      <location>Collections/WalkerCollection</location>
      <ownership>true</ownership>
      <date>Sat Jan 30 10:18:39 EST 2016</date>
    </mcp>
    <mcp>
      <card>
        <id>407514</id>
        <name>Kozilek, the Great Distortion</name>
        <edition>Oath of the Gatewatch</edition>
      </card>
      <count>1</count>
      <location>Collections/WalkerCollection</location>
      <ownership>true</ownership>
      <date>Sat Jan 30 10:21:47 EST 2016</date>
    </mcp>
    <mcp>
      <card>
        <id>368548</id>
        <name>Vithian Stinger</name>
        <edition>Duel Decks: Sorin vs. Tibalt</edition>
      </card>
      <count>2</count>
      <location>Collections/WalkerCollection</location>
      <ownership>true</ownership>
      <date>Sat Jan 30 10:28:18 EST 2016</date>
    </mcp>
    <mcp>
      <card>
        <id>368526</id>
        <name>Lavaborn Muse</name>
        <edition>Duel Decks: Sorin vs. Tibalt</edition>
      </card>
      <count>1</count>
      <location>Collections/WalkerCollection</location>
      <ownership>true</ownership>
      <date>Sat Jan 30 10:28:41 EST 2016</date>
    </mcp>
    <mcp>
      <card>
        <id>368545</id>
        <name>Pyroclasm</name>
        <edition>Duel Decks: Sorin vs. Tibalt</edition>
      </card>
      <count>1</count>
      <location>Collections/WalkerCollection</location>
      <ownership>true</ownership>
      <date>Sat Jan 30 10:29:03 EST 2016</date>
    </mcp>
    <mcp>
      <card>
        <id>368477</id>
        <name>Hellspark Elemental</name>
        <edition>Duel Decks: Sorin vs. Tibalt</edition>
      </card>
      <count>3</count>
      <location>Collections/WalkerCollection</location>
      <ownership>true</ownership>
      <date>Sat Jan 30 10:29:28 EST 2016</date>
    </mcp>
    <mcp>
      <card>
        <id>368536</id>
        <name>Flame Slash</name>
        <edition>Duel Decks: Sorin vs. Tibalt</edition>
      </card>
      <count>2</count>
      <location>Collections/WalkerCollection</location>
      <ownership>true</ownership>
      <date>Sat Jan 30 10:29:58 EST 2016</date>
    </mcp>
    <mcp>
      <card>
        <id>368489</id>
        <name>Shambling Remains</name>
        <edition>Duel Decks: Sorin vs. Tibalt</edition>
      </card>
      <count>1</count>
      <location>Collections/WalkerCollection</location>
      <ownership>true</ownership>
      <date>Sat Jan 30 10:30:13 EST 2016</date>
    </mcp>
    <mcp>
      <card>
        <id>368530</id>
        <name>Hellrider</name>
        <edition>Duel Decks: Sorin vs. Tibalt</edition>
      </card>
      <count>1</count>
      <location>Collections/WalkerCollection</location>
      <ownership>true</ownership>
      <date>Sat Jan 30 10:30:55 EST 2016</date>
    </mcp>
    <mcp>
      <card>
        <id>368528</id>
        <name>Browbeat</name>
        <edition>Duel Decks: Sorin vs. Tibalt</edition>
      </card>
      <count>2</count>
      <location>Collections/WalkerCollection</location>
      <ownership>true</ownership>
      <date>Sat Jan 30 10:31:10 EST 2016</date>
    </mcp>
    <mcp>
      <card>
        <id>368486</id>
        <name>Breaking Point</name>
        <edition>Duel Decks: Sorin vs. Tibalt</edition>
      </card>
      <count>1</count>
      <location>Collections/WalkerCollection</location>
      <ownership>true</ownership>
      <date>Sat Jan 30 10:31:28 EST 2016</date>
    </mcp>
    <mcp>
      <card>
        <id>368550</id>
        <name>Sulfuric Vortex</name>
        <edition>Duel Decks: Sorin vs. Tibalt</edition>
      </card>
      <count>1</count>
      <location>Collections/WalkerCollection</location>
      <ownership>true</ownership>
      <date>Sat Jan 30 10:32:02 EST 2016</date>
    </mcp>
    <mcp>
      <card>
        <id>368533</id>
        <name>Coal Stoker</name>
        <edition>Duel Decks: Sorin vs. Tibalt</edition>
      </card>
      <count>2</count>
      <location>Collections/WalkerCollection</location>
      <ownership>true</ownership>
      <date>Sat Jan 30 10:32:45 EST 2016</date>
    </mcp>
    <mcp>
      <card>
        <id>368491</id>
        <name>Terminate</name>
        <edition>Duel Decks: Sorin vs. Tibalt</edition>
      </card>
      <count>1</count>
      <location>Collections/WalkerCollection</location>
      <ownership>true</ownership>
      <date>Sat Jan 30 10:32:59 EST 2016</date>
    </mcp>
    <mcp>
      <card>
        <id>368539</id>
        <name>Gang of Devils</name>
        <edition>Duel Decks: Sorin vs. Tibalt</edition>
      </card>
      <count>1</count>
      <location>Collections/WalkerCollection</location>
      <ownership>true</ownership>
      <date>Sat Jan 30 10:33:21 EST 2016</date>
    </mcp>
    <mcp>
      <card>
        <id>368504</id>
        <name>Scorched Rusalka</name>
        <edition>Duel Decks: Sorin vs. Tibalt</edition>
      </card>
      <count>1</count>
      <location>Collections/WalkerCollection</location>
      <ownership>true</ownership>
      <date>Sat Jan 30 10:33:36 EST 2016</date>
    </mcp>
    <mcp>
      <card>
        <id>368517</id>
        <name>Recoup</name>
        <edition>Duel Decks: Sorin vs. Tibalt</edition>
      </card>
      <count>1</count>
      <location>Collections/WalkerCollection</location>
      <ownership>true</ownership>
      <date>Sat Jan 30 10:33:54 EST 2016</date>
    </mcp>
    <mcp>
      <card>
        <id>368513</id>
        <name>Scourge Devil</name>
        <edition>Duel Decks: Sorin vs. Tibalt</edition>
      </card>
      <count>2</count>
      <location>Collections/WalkerCollection</location>
      <ownership>true</ownership>
      <date>Sat Jan 30 10:34:22 EST 2016</date>
    </mcp>
    <mcp>
      <card>
        <id>368523</id>
        <name>Akoum Refuge</name>
        <edition>Duel Decks: Sorin vs. Tibalt</edition>
      </card>
      <count>2</count>
      <location>Collections/WalkerCollection</location>
      <ownership>true</ownership>
      <date>Sat Jan 30 10:34:29 EST 2016</date>
    </mcp>
    <mcp>
      <card>
        <id>368551</id>
        <name>Reassembling Skeleton</name>
        <edition>Duel Decks: Sorin vs. Tibalt</edition>
      </card>
      <count>1</count>
      <location>Collections/WalkerCollection</location>
      <ownership>true</ownership>
      <date>Sat Jan 30 10:34:53 EST 2016</date>
    </mcp>
    <mcp>
      <card>
        <id>368487</id>
        <name>Corpse Connoisseur</name>
        <edition>Duel Decks: Sorin vs. Tibalt</edition>
      </card>
      <count>1</count>
      <location>Collections/WalkerCollection</location>
      <ownership>true</ownership>
      <date>Sat Jan 30 10:35:16 EST 2016</date>
    </mcp>
    <mcp>
      <card>
        <id>368511</id>
        <name>Torrent of Souls</name>
        <edition>Duel Decks: Sorin vs. Tibalt</edition>
      </card>
      <count>1</count>
      <location>Collections/WalkerCollection</location>
      <ownership>true</ownership>
      <date>Sat Jan 30 10:35:39 EST 2016</date>
    </mcp>
    <mcp>
      <card>
        <id>368531</id>
        <name>Tibalt, the Fiend-Blooded</name>
        <edition>Duel Decks: Sorin vs. Tibalt</edition>
      </card>
      <count>1</count>
      <location>Collections/WalkerCollection</location>
      <ownership>true</ownership>
      <date>Sat Jan 30 10:35:59 EST 2016</date>
    </mcp>
    <mcp>
      <card>
        <id>368474</id>
        <name>Mad Prophet</name>
        <edition>Duel Decks: Sorin vs. Tibalt</edition>
      </card>
      <count>3</count>
      <location>Collections/WalkerCollection</location>
      <ownership>true</ownership>
      <date>Sat Jan 30 10:36:45 EST 2016</date>
    </mcp>
    <mcp>
      <card>
        <id>368483</id>
        <name>Blightning</name>
        <edition>Duel Decks: Sorin vs. Tibalt</edition>
      </card>
      <count>1</count>
      <location>Collections/WalkerCollection</location>
      <ownership>true</ownership>
      <date>Sat Jan 30 10:36:57 EST 2016</date>
    </mcp>
    <mcp>
      <card>
        <id>368476</id>
        <name>Ashmouth Hound</name>
        <edition>Duel Decks: Sorin vs. Tibalt</edition>
      </card>
      <count>2</count>
      <location>Collections/WalkerCollection</location>
      <ownership>true</ownership>
      <date>Sat Jan 30 10:37:20 EST 2016</date>
    </mcp>
    <mcp>
      <card>
        <id>368478</id>
        <name>Goblin Arsonist</name>
        <edition>Duel Decks: Sorin vs. Tibalt</edition>
      </card>
      <count>1</count>
      <location>Collections/WalkerCollection</location>
      <ownership>true</ownership>
      <date>Sat Jan 30 10:37:46 EST 2016</date>
    </mcp>
    <mcp>
      <card>
        <id>368524</id>
        <name>Geistflame</name>
        <edition>Duel Decks: Sorin vs. Tibalt</edition>
      </card>
      <count>1</count>
      <location>Collections/WalkerCollection</location>
      <ownership>true</ownership>
      <date>Sat Jan 30 10:38:47 EST 2016</date>
    </mcp>
    <mcp>
      <card>
        <id>368493</id>
        <name>Rakdos Carnarium</name>
        <edition>Duel Decks: Sorin vs. Tibalt</edition>
      </card>
      <count>2</count>
      <location>Collections/WalkerCollection</location>
      <ownership>true</ownership>
      <date>Sat Jan 30 10:39:05 EST 2016</date>
    </mcp>
    <mcp>
      <card>
        <id>368544</id>
        <name>Flame Javelin</name>
        <edition>Duel Decks: Sorin vs. Tibalt</edition>
      </card>
      <count>2</count>
      <location>Collections/WalkerCollection</location>
      <ownership>true</ownership>
      <date>Sat Jan 30 10:39:27 EST 2016</date>
    </mcp>
    <mcp>
      <card>
        <id>368475</id>
        <name>Faithless Looting</name>
        <edition>Duel Decks: Sorin vs. Tibalt</edition>
      </card>
      <count>1</count>
      <location>Collections/WalkerCollection</location>
      <ownership>true</ownership>
      <date>Sat Jan 30 10:39:46 EST 2016</date>
    </mcp>
    <mcp>
      <card>
        <id>368507</id>
        <name>Blazing Salvo</name>
        <edition>Duel Decks: Sorin vs. Tibalt</edition>
      </card>
      <count>1</count>
      <location>Collections/WalkerCollection</location>
      <ownership>true</ownership>
      <date>Sat Jan 30 10:40:12 EST 2016</date>
    </mcp>
    <mcp>
      <card>
        <id>368488</id>
        <name>Skirsdag Cultist</name>
        <edition>Duel Decks: Sorin vs. Tibalt</edition>
      </card>
      <count>1</count>
      <location>Collections/WalkerCollection</location>
      <ownership>true</ownership>
      <date>Sat Jan 30 10:40:57 EST 2016</date>
    </mcp>
    <mcp>
      <card>
        <id>368518</id>
        <name>Devil's Play</name>
        <edition>Duel Decks: Sorin vs. Tibalt</edition>
      </card>
      <count>1</count>
      <location>Collections/WalkerCollection</location>
      <ownership>true</ownership>
      <date>Sat Jan 30 10:41:11 EST 2016</date>
    </mcp>
    <mcp>
      <card>
        <id>368521</id>
        <name>Strangling Soot</name>
        <edition>Duel Decks: Sorin vs. Tibalt</edition>
      </card>
      <count>1</count>
      <location>Collections/WalkerCollection</location>
      <ownership>true</ownership>
      <date>Sat Jan 30 10:41:23 EST 2016</date>
    </mcp>
    <mcp>
      <card>
        <id>368490</id>
        <name>Bump in the Night</name>
        <edition>Duel Decks: Sorin vs. Tibalt</edition>
      </card>
      <count>1</count>
      <location>Collections/WalkerCollection</location>
      <ownership>true</ownership>
      <date>Sat Jan 30 10:41:33 EST 2016</date>
    </mcp>
    <mcp>
      <card>
        <id>253591</id>
        <name>Rakdos Shred-Freak</name>
        <edition>Return to Ravnica</edition>
      </card>
      <count>4</count>
      <location>Collections/WalkerCollection</location>
      <ownership>true</ownership>
      <date>Sat Jan 30 10:45:27 EST 2016</date>
    </mcp>
    <mcp>
      <card>
        <id>253596</id>
        <name>Rakdos Cackler</name>
        <edition>Return to Ravnica</edition>
      </card>
      <count>4</count>
      <location>Collections/WalkerCollection</location>
      <ownership>true</ownership>
      <date>Sat Jan 30 10:46:09 EST 2016</date>
    </mcp>
    <mcp>
      <card>
        <id>245184</id>
        <name>Shock</name>
        <edition>Magic 2012</edition>
      </card>
      <count>3</count>
      <location>Collections/WalkerCollection</location>
      <ownership>true</ownership>
      <date>Sat Jan 30 10:46:54 EST 2016</date>
    </mcp>
    <mcp>
      <card>
        <id>386365</id>
        <name>Shock</name>
        <edition>Duel Decks: Speed vs. Cunning</edition>
      </card>
      <count>1</count>
      <location>Collections/WalkerCollection</location>
      <ownership>true</ownership>
      <date>Sat Jan 30 10:47:03 EST 2016</date>
    </mcp>
    <mcp>
      <card>
        <id>373698</id>
        <name>Minotaur Skullcleaver</name>
        <edition>Theros</edition>
      </card>
      <count>4</count>
      <location>Collections/WalkerCollection</location>
      <ownership>true</ownership>
      <date>Sat Jan 30 10:47:32 EST 2016</date>
    </mcp>
    <mcp>
      <card>
        <id>366377</id>
        <name>Madcap Skills</name>
        <edition>Gatecrash</edition>
      </card>
      <count>4</count>
      <location>Collections/WalkerCollection</location>
      <ownership>true</ownership>
      <date>Sat Jan 30 10:48:32 EST 2016</date>
    </mcp>
  </list>
</cards>